<?xml version="1.0" encoding="UTF-8"?>
<metadata>
    <name>Abandoned Laboratory</name>
    <directory>abandoned_laboratory</directory>
    <id>2491235243</id>
    <description>Abandoned Laboratory is a currently a work in progress.  It will eventually be a tech-themed general expansion mod.</description>
    <version>0.12.2</version>
    <visibility>Private</visibility>
    <tag id="Lua"/>
    <tag id="Items"/>
    <tag id="Active Items"/>
    <tag id="Trinkets"/>
    <tag id="Pickups"/>
    <tag id="Player Characters"/>
    <tag id="Familiars"/>
    <tag id="Rooms"/>
    <tag id="Floors"/>
    <tag id="Enemies"/>
    <tag id="Bosses"/>
    <tag id="Hazards"/>
    <tag id="Challenges"/>
    <tag id="Graphics"/>
    <tag id="Sound Effects"/>
    <tag id="Music"/>
</metadata>
